<?xml version="1.0" encoding="utf-8"?>
<fmg>
<compression>None</compression>
<version>DarkSouls3</version>
<bigendian>False</bigendian>
<entries>
<text id="402400">米尔伍德大箭</text>
<text id="2240000">隆道尔之誓</text>
<text id="2240100">致命隆道尔之誓</text>
<text id="2240200">诅咒隆道尔之誓</text>
<text id="2240300">毒隆道尔之誓</text>
<text id="2240400">血隆道尔之誓</text>
<text id="2240500">霜冻隆道尔之誓</text>
<text id="2240600">魔力隆道尔之誓</text>
<text id="2240700">火焰隆道尔之誓</text>
<text id="2240800">雷电隆道尔之誓</text>
<text id="2240900">暗隆道尔之誓</text>
<text id="2241000">幸运隆道尔之誓</text>
<text id="2241100">附魔隆道尔之誓</text>
<text id="2241200">祝福隆道尔之誓</text>
<text id="2241300">锋利隆道尔之誓</text>
<text id="2241400">厚重隆道尔之誓</text>
<text id="4120000">幽魂军刀</text>
<text id="4120100">致命幽魂军刀</text>
<text id="4120200">诅咒幽魂军刀</text>
<text id="4120300">毒幽魂军刀</text>
<text id="4120400">血幽魂军刀</text>
<text id="4120500">霜冻幽魂军刀</text>
<text id="4120600">魔力幽魂军刀</text>
<text id="4120700">火焰幽魂军刀</text>
<text id="4120800">雷电幽魂军刀</text>
<text id="4120900">暗幽魂军刀</text>
<text id="4121000">幸运幽魂军刀</text>
<text id="4121100">附魔幽魂军刀</text>
<text id="4121200">祝福幽魂军刀</text>
<text id="4121300">锋利幽魂军刀</text>
<text id="4121400">厚重幽魂军刀</text>
<text id="7170000">米尔伍德战斧</text>
<text id="7170100">致命米尔伍德战斧</text>
<text id="7170200">诅咒米尔伍德战斧</text>
<text id="7170300">毒米尔伍德战斧</text>
<text id="7170400">血米尔伍德战斧</text>
<text id="7170500">霜冻米尔伍德战斧</text>
<text id="7170600">魔力米尔伍德战斧</text>
<text id="7170700">火焰米尔伍德战斧</text>
<text id="7170800">雷电米尔伍德战斧</text>
<text id="7170900">暗米尔伍德战斧</text>
<text id="7171000">幸运米尔伍德战斧</text>
<text id="7171100">附魔米尔伍德战斧</text>
<text id="7171200">祝福米尔伍德战斧</text>
<text id="7171300">锋利米尔伍德战斧</text>
<text id="7171400">厚重米尔伍德战斧</text>
<text id="7180000">追地者</text>
<text id="7180100">致命追地者</text>
<text id="7180200">诅咒追地者</text>
<text id="7180300">毒追地者</text>
<text id="7180400">血追地者</text>
<text id="7180500">霜冻追地者</text>
<text id="7180600">魔力追地者</text>
<text id="7180700">火焰追地者</text>
<text id="7180800">雷电追地者</text>
<text id="7180900">暗追地者</text>
<text id="7181000">幸运追地者</text>
<text id="7181100">附魔追地者</text>
<text id="7181200">祝福追地者</text>
<text id="7181300">锋利追地者</text>
<text id="7181400">厚重追地者</text>
<text id="8310000">地鸣岩槌</text>
<text id="8310100">致命地鸣岩槌</text>
<text id="8310200">诅咒地鸣岩槌</text>
<text id="8310300">毒地鸣岩槌</text>
<text id="8310400">血地鸣岩槌</text>
<text id="8310500">霜冻地鸣岩槌</text>
<text id="8310600">魔力地鸣岩槌</text>
<text id="8310700">火焰地鸣岩槌</text>
<text id="8310800">雷电地鸣岩槌</text>
<text id="8310900">暗地鸣岩槌</text>
<text id="8311000">幸运地鸣岩槌</text>
<text id="8311100">附魔地鸣岩槌</text>
<text id="8311200">祝福地鸣岩槌</text>
<text id="8311300">锋利地鸣岩槌</text>
<text id="8311400">厚重地鸣岩槌</text>
<text id="9230000">幽魂投枪</text>
<text id="9230100">致命幽魂投枪</text>
<text id="9230200">诅咒幽魂投枪</text>
<text id="9230300">毒幽魂投枪</text>
<text id="9230400">血幽魂投枪</text>
<text id="9230500">霜冻幽魂投枪</text>
<text id="9230600">魔力幽魂投枪</text>
<text id="9230700">火焰幽魂投枪</text>
<text id="9230800">雷电幽魂投枪</text>
<text id="9230900">暗幽魂投枪</text>
<text id="9231000">幸运幽魂投枪</text>
<text id="9231100">附魔幽魂投枪</text>
<text id="9231200">祝福幽魂投枪</text>
<text id="9231300">锋利幽魂投枪</text>
<text id="9231400">厚重幽魂投枪</text>
<text id="10180000">芙莉德大镰刀</text>
<text id="10180100">致命芙莉德大镰刀</text>
<text id="10180200">诅咒芙莉德大镰刀</text>
<text id="10180300">毒芙莉德大镰刀</text>
<text id="10180400">血芙莉德大镰刀</text>
<text id="10180500">霜冻芙莉德大镰刀</text>
<text id="10180600">魔力芙莉德大镰刀</text>
<text id="10180700">火焰芙莉德大镰刀</text>
<text id="10180800">雷电芙莉德大镰刀</text>
<text id="10180900">暗芙莉德大镰刀</text>
<text id="10181000">幸运芙莉德大镰刀</text>
<text id="10181100">附魔芙莉德大镰刀</text>
<text id="10181200">祝福芙莉德大镰刀</text>
<text id="10181300">厚重芙莉德大镰刀</text>
<text id="10181400">锋利芙莉德大镰刀</text>
<text id="11050000">鸦爪</text>
<text id="11050100">致命鸦爪</text>
<text id="11050200">诅咒鸦爪</text>
<text id="11050300">毒鸦爪</text>
<text id="11050400">血鸦爪</text>
<text id="11050500">霜冻鸦爪</text>
<text id="11050600">魔力鸦爪</text>
<text id="11050700">火焰鸦爪</text>
<text id="11050800">雷电鸦爪</text>
<text id="11050900">暗鸦爪</text>
<text id="11051000">幸运鸦爪</text>
<text id="11051100">祝福鸦爪</text>
<text id="11051200">附魔鸦爪</text>
<text id="11051300">锋利鸦爪</text>
<text id="11051400">厚重鸦爪</text>
<text id="12070000">艾雷德尔蔷薇</text>
<text id="12070100">致命艾雷德尔蔷薇</text>
<text id="12070200">诅咒艾雷德尔蔷薇</text>
<text id="12070300">毒艾雷德尔蔷薇</text>
<text id="12070400">血艾雷德尔蔷薇</text>
<text id="12070500">霜冻艾雷德尔蔷薇</text>
<text id="12070600">魔力艾雷德尔蔷薇</text>
<text id="12070700">火焰艾雷德尔蔷薇</text>
<text id="12070800">雷电艾雷德尔蔷薇</text>
<text id="12070900">暗艾雷德尔蔷薇</text>
<text id="12071000">幸运艾雷德尔蔷薇</text>
<text id="12071100">附魔艾雷德尔蔷薇</text>
<text id="12071200">祝福艾雷德尔蔷薇</text>
<text id="12071300">锋利艾雷德尔蔷薇</text>
<text id="12071400">厚重艾雷德尔蔷薇</text>
<text id="13410000">咒术送灵火</text>
<text id="14180000">米尔伍德大弓</text>
<text id="16140000">果敢心</text>
<text id="16140100">致命果敢心</text>
<text id="16140200">诅咒果敢心</text>
<text id="16140300">毒果敢心</text>
<text id="16140400">血果敢心</text>
<text id="16140500">霜冻果敢心</text>
<text id="16140600">魔力果敢心</text>
<text id="16140700">火焰果敢心</text>
<text id="16140800">雷电果敢心</text>
<text id="16140900">暗果敢心</text>
<text id="16141000">幸运果敢心</text>
<text id="16141100">附魔果敢心</text>
<text id="16141200">祝福果敢心</text>
<text id="16141300">锋利果敢心</text>
<text id="16141400">厚重果敢心</text>
<text id="16150000">鸦羽</text>
<text id="16150100">致命鸦羽</text>
<text id="16150200">诅咒鸦羽</text>
<text id="16150300">毒鸦羽</text>
<text id="16150400">血鸦羽</text>
<text id="16150500">霜冻鸦羽</text>
<text id="16150600">魔力鸦羽</text>
<text id="16150700">火焰鸦羽</text>
<text id="16150800">雷电鸦羽</text>
<text id="16150900">暗鸦羽</text>
<text id="16151000">幸运鸦羽</text>
<text id="16151100">附魔鸦羽</text>
<text id="16151200">祝福鸦羽</text>
<text id="16151300">锋利鸦羽</text>
<text id="16151400">厚重鸦羽</text>
<text id="20300000">幽魂盾</text>
<text id="20300100">明晰幽魂盾</text>
<text id="20300200">活力幽魂盾</text>
<text id="20300300">治疗幽魂盾</text>
<text id="20300400">健壮幽魂盾</text>
<text id="20300500">清明幽魂盾</text>
<text id="20300600">贪婪幽魂盾</text>
<text id="20300700">魔力幽魂盾</text>
<text id="20300800">火焰幽魂盾</text>
<text id="20300900">雷电幽魂盾</text>
<text id="20301000">暗幽魂盾</text>
<text id="21300000">灵树盾</text>
<text id="21300100">明晰灵树盾</text>
<text id="21300200">活力灵树盾</text>
<text id="21300300">治疗灵树盾</text>
<text id="21300400">健壮灵树盾</text>
<text id="21300500">清明灵树盾</text>
<text id="21300600">贪婪灵树盾</text>
<text id="21300700">魔力灵树盾</text>
<text id="21300800">火焰灵树盾</text>
<text id="21300900">雷电灵树盾</text>
<text id="21301000">暗灵树盾</text>
<text id="23010000">幽魂火把</text>
<text id="23010100">致命幽魂火把</text>
<text id="23010200">诅咒幽魂火把</text>
<text id="23010300">毒幽魂火把</text>
<text id="23010400">血幽魂火把</text>
<text id="23010500">霜冻幽魂火把</text>
<text id="23010600">魔力幽魂火把</text>
<text id="23010700">火焰幽魂火把</text>
<text id="23010800">雷电幽魂火把</text>
<text id="23010900">暗幽魂火把</text>
<text id="23011000">幸运幽魂火把</text>
<text id="23011100">附魔幽魂火把</text>
<text id="23011200">祝福幽魂火把</text>
<text id="23011300">锋利幽魂火把</text>
<text id="23011400">厚重幽魂火把</text>
</entries>
</fmg>